inginx/__init__.py
inginx/inginx.py
inginx-0.3.18.dist-info/WHEEL
inginx-0.3.18.dist-info/entry_points.txt
inginx-0.3.18.dist-info/METADATA
inginx-0.3.18.dist-info/RECORD
