Metadata-Version: 2.3
Name: inginx
Version: 0.3.18
Summary: Add your description here
Author: Richard Hajek
Author-email: Richard Hajek <richard.m.hajek@gmail.com>
Requires-Python: >=3.12
